adancfgd/__init__.py
adancfgd/adancfgd.py
adancfgd/snn.py
adancfgd/snn_cnn.py
adancfgd-0.1.5.dist-info/licenses/LICENSE
adancfgd-0.1.5.dist-info/METADATA
adancfgd-0.1.5.dist-info/WHEEL
adancfgd-0.1.5.dist-info/top_level.txt
adancfgd-0.1.5.dist-info/RECORD
