Metadata-Version: 2.4
Name: adancfgd
Version: 0.1.5
Summary: Adaptive Fractional Gradient Descent Optimizers (AdaFGD & AdaNCFGD)
Home-page: https://github.com/HunLuanZhiZhu/AdaNCFGD
Author: Yihe Zhu
Author-email: zhu.yihe@qq.com
License: MIT
Keywords: optimizers,fractional-calculus,pytorch,machine-learning,deep-learning,spiking-neural-networks
Classifier: Programming Language :: Python :: 3
Classifier: Programming Language :: Python :: 3.6
Classifier: Programming Language :: Python :: 3.7
Classifier: Programming Language :: Python :: 3.8
Classifier: Programming Language :: Python :: 3.9
Classifier: Programming Language :: Python :: 3.10
Classifier: Operating System :: OS Independent
Classifier: Intended Audience :: Developers
Classifier: Intended Audience :: Science/Research
Classifier: Topic :: Scientific/Engineering
Classifier: Topic :: Scientific/Engineering :: Artificial Intelligence
Classifier: Topic :: Software Development
Classifier: Topic :: Software Development :: Libraries
Classifier: Topic :: Software Development :: Libraries :: Python Modules
License-File: LICENSE
Requires-Dist: torch>=1.7.0
Requires-Dist: numpy
Provides-Extra: test
Requires-Dist: pytest>=6.0; extra == "test"
Requires-Dist: torchvision; extra == "test"
Requires-Dist: tqdm; extra == "test"
Dynamic: license-file
